arkaine/__init__.py
arkaine/events.py
arkaine/quickstart.py
arkaine/backends/__init__.py
arkaine/backends/backend.py
arkaine/backends/common.py
arkaine/backends/google.py
arkaine/backends/jobboard.py
arkaine/backends/ollama.py
arkaine/backends/openai.py
arkaine/backends/python.py
arkaine/backends/react.py
arkaine/backends/simple.py
arkaine/backends/prompts/python.prompt
arkaine/backends/prompts/python_followup.prompt
arkaine/backends/prompts/python_judge.prompt
arkaine/backends/prompts/react.prompt
arkaine/backends/prompts/simple.prompt
arkaine/chat/__init__.py
arkaine/chat/chat.py
arkaine/chat/conversation.py
arkaine/chat/simple.py
arkaine/chat/prompts/conversation_continuation.prompt
arkaine/chat/prompts/conversation_label.prompt
arkaine/chat/prompts/generate_response.prompt
arkaine/chat/prompts/task_identification.prompt
arkaine/connectors/__init__.py
arkaine/connectors/api.py
arkaine/connectors/cli.py
arkaine/connectors/inbox.py
arkaine/connectors/rss.py
arkaine/connectors/schedule.py
arkaine/flow/__init__.py
arkaine/flow/branch.py
arkaine/flow/conditional.py
arkaine/flow/dowhile.py
arkaine/flow/fire_and_forget.py
arkaine/flow/linear.py
arkaine/flow/on_error.py
arkaine/flow/parallel_list.py
arkaine/flow/retry.py
arkaine/internal/__init__.py
arkaine/internal/json.py
arkaine/internal/to_json.py
arkaine/internal/logging/__init__.py
arkaine/internal/logging/logger.py
arkaine/internal/options/__init__.py
arkaine/internal/options/context.py
arkaine/internal/registrar/__init__.py
arkaine/internal/registrar/registrar.py
arkaine/internal/store/__init__.py
arkaine/internal/store/context.py
arkaine/internal/store/embeddings.py
arkaine/llms/__init__.py
arkaine/llms/claude.py
arkaine/llms/deepseek.py
arkaine/llms/google.py
arkaine/llms/groq.py
arkaine/llms/llm.py
arkaine/llms/loader.py
arkaine/llms/ollama.py
arkaine/llms/openai.py
arkaine/plugins/website/arxiv.py
arkaine/plugins/website/tavily.py
arkaine/plugins/website/youtube.py
arkaine/spellbook/__init__.py
arkaine-0.0.24.dist-info/licenses/LICENSE
arkaine-0.0.24.dist-info/METADATA
arkaine-0.0.24.dist-info/WHEEL
arkaine-0.0.24.dist-info/entry_points.txt
arkaine-0.0.24.dist-info/top_level.txt
arkaine-0.0.24.dist-info/RECORD
