Metadata-Version: 2.4
Name: arkaine
Version: 0.0.24
Summary: A batteries-included framework for DIY AI agents
Author-email: Keith Chester <keith@hlfshell.ai>
License: MIT License
Project-URL: Homepage, https://github.com/hlfshell/arkaine
Project-URL: Documentation, https://arkaine.readthedocs.io/
Project-URL: Repository, https://github.com/hlfshell/arkaine.git
Classifier: Development Status :: 3 - Alpha
Classifier: Intended Audience :: Developers
Classifier: License :: OSI Approved :: MIT License
Classifier: Operating System :: OS Independent
Classifier: Programming Language :: Python :: 3
Classifier: Programming Language :: Python :: 3.8
Classifier: Programming Language :: Python :: 3.9
Classifier: Programming Language :: Python :: 3.10
Classifier: Programming Language :: Python :: 3.11
Requires-Python: >=3.8
License-File: LICENSE
Requires-Dist: anthropic==0.49.0
Requires-Dist: groq==0.18.0
Requires-Dist: openai==1.68.0
Requires-Dist: google-generativeai==0.8.4
Requires-Dist: ollama==0.4.7
Requires-Dist: fastapi==0.115.8
Requires-Dist: uvicorn==0.34.0
Requires-Dist: websockets==14.1
Requires-Dist: Requests==2.32.3
Requires-Dist: tldextract==5.1.3
Requires-Dist: docker==7.1.0
Requires-Dist: numpy==2.2.2
Requires-Dist: scikit_learn==1.6.1
Requires-Dist: beautifulsoup4==4.13.1
Requires-Dist: markdownify==0.13.1
Requires-Dist: pydantic==2.10.6
Requires-Dist: PyJWT==2.10.1
Requires-Dist: click==8.1.8
Requires-Dist: feedparser==6.0.11
Requires-Dist: parsedatetime==2.6
Requires-Dist: pytz==2024.2
Requires-Dist: typing_extensions==4.12.2
Requires-Dist: pymupdf4llm==0.0.17
Requires-Dist: wikipedia==1.4.0
Requires-Dist: googlemaps==4.10.0
Requires-Dist: setuptools==75.8.0
Dynamic: license-file
